robodroid/__init__.py
robodroid/config/metadata.json
robodroid/config/template.yaml
robodroid/main.py
robodroid/services/__init__.py
robodroid/services/adb.py
robodroid/services/frida.py
robodroid/tests/assets/InsecureBankv2.apk
robodroid/tests/test_adb.py
robodroid/tests/test_config.py
robodroid/tests/test_helpers.py
robodroid/types/__init__.py
robodroid/types/common.py
robodroid/types/enum.py
robodroid/utils/__init__.py
robodroid/utils/constants.py
robodroid/utils/exceptions.py
robodroid/utils/helper.py
robodroid/utils/logger.py
robodroid/utils/schemas.py
robodroid/workflow/__init__.py
robodroid/workflow/commands.py
robodroid/workflow/config.py
robodroid/workflow/manager.py
robodroid-0.0.3.dist-info/LICENSE
robodroid-0.0.3.dist-info/METADATA
robodroid-0.0.3.dist-info/WHEEL
robodroid-0.0.3.dist-info/entry_points.txt
robodroid-0.0.3.dist-info/RECORD
