Metadata-Version: 2.1
Name: robodroid
Version: 0.0.3
Summary: Manage and deploy Android machines with pre-defined behaviors for Cyber Range environments
License: GPL-3.0
Author: Angelo Delicato
Author-email: thelicato@duck.com
Requires-Python: >=3.9,<4.0
Classifier: License :: OSI Approved :: GNU General Public License v3 (GPLv3)
Classifier: Programming Language :: Python :: 3
Classifier: Programming Language :: Python :: 3.9
Classifier: Programming Language :: Python :: 3.10
Classifier: Programming Language :: Python :: 3.11
Classifier: Programming Language :: Python :: 3.12
Requires-Dist: cerberus (>=1.3.4,<2.0.0)
Requires-Dist: frida (>=16.0.11,<17.0.0)
Requires-Dist: pure-python-adb (==0.3.*)
Requires-Dist: pyhumps (>=3.8.0,<4.0.0)
Requires-Dist: pylint (==2.15.8)
Requires-Dist: pyyaml (>=6.0,<7.0)
Requires-Dist: questionary (==2.0.1)
Requires-Dist: requests (==2.31.0)
Requires-Dist: tenacity (>=8.2.2,<9.0.0)
Requires-Dist: typer (==0.9.0)
Requires-Dist: typing-extensions (>=4.5.0,<5.0.0)
Requires-Dist: wrapt-timeout-decorator (>=1.3.12.2,<2.0.0.0)
